pogodata/__init__.py
pogodata/enums.py
pogodata/game_objects.py
pogodata/grunt_characters.py
pogodata/misc.py
pogodata/mons.py
pogodata/moves.py
pogodata/objects.py
pogodata/pogodata.py
pogodata/pokemon.py
pogodata/util.py
pogodata/pogoinfo/full_grunts.py
pogodata/pogoinfo/pogoinfo.py
pogodata/pogoinfo/raids.py
pogodata-0.5.14.dist-info/METADATA
pogodata-0.5.14.dist-info/WHEEL
pogodata-0.5.14.dist-info/top_level.txt
pogodata-0.5.14.dist-info/RECORD
