Metadata-Version: 2.1
Name: pogodata
Version: 0.5.14
Summary: Easy and up-to-date Pogo Data
Home-page: https://github.com/ccev/pogodata
Author: ccev
Author-email: UNKNOWN
License: UNKNOWN
Platform: UNKNOWN
Requires-Dist: requests
